exam_terminal/ExamTerminal.py
exam_terminal/__init__.py
exam_terminal/__main__.py
exam_terminal/exam_terminal.py
exam_terminal/utility.py
exam_terminal/exams/sample_exam.yml
exam_terminal-0.2.13.dist-info/licenses/LICENSE
exam_terminal-0.2.13.dist-info/METADATA
exam_terminal-0.2.13.dist-info/WHEEL
exam_terminal-0.2.13.dist-info/entry_points.txt
exam_terminal-0.2.13.dist-info/top_level.txt
exam_terminal-0.2.13.dist-info/RECORD
