Metadata-Version: 2.4
Name: exam-terminal
Version: 0.2.13
Summary: A terminal-based exam, text, or survey tool for educators and learners
Home-page: https://github.com/ismet55555/exam-terminal
Author: Ismet Handzic
Author-email: ismet.handzic@gmail.com
Maintainer: Ismet Handzic
Keywords: exam quiz assessment survey teach learn
Classifier: Development Status :: 4 - Beta
Classifier: Topic :: Education
Classifier: License :: OSI Approved :: Apache Software License
Classifier: Natural Language :: English
Classifier: Intended Audience :: Education
Classifier: Topic :: Education
Classifier: Topic :: Education :: Testing
Classifier: Topic :: Software Development :: Libraries :: Python Modules
Classifier: Environment :: Console
Classifier: Environment :: Console :: Curses
Classifier: Operating System :: OS Independent
Classifier: Programming Language :: Python :: 3 :: Only
Requires-Python: >=3.7
License-File: LICENSE
Requires-Dist: PyYAML==6.0
Requires-Dist: click==8.2
Requires-Dist: fpdf2==2.7
Requires-Dist: pypiwin32; platform_system == "Windows"
Requires-Dist: pywin32; platform_system == "Windows"
Requires-Dist: requests==2.31
Requires-Dist: wheel==0.42
Requires-Dist: windows-curses; sys_platform == "win32"
Dynamic: author
Dynamic: author-email
Dynamic: classifier
Dynamic: description
Dynamic: description-content-type
Dynamic: home-page
Dynamic: keywords
Dynamic: license-file
Dynamic: maintainer
Dynamic: requires-dist
Dynamic: requires-python
Dynamic: summary
